matugen/__main__.py
matugen/util.py
matugen-0.4.1.dist-info/entry_points.txt
matugen-0.4.1.dist-info/WHEEL
matugen-0.4.1.dist-info/METADATA
matugen-0.4.1.dist-info/RECORD
