Metadata-Version: 2.1
Name: matugen
Version: 0.4.1
Summary: 
Author: InioX
Author-email: justimnix@gmail.com
Requires-Python: >=3.10,<4.0
Classifier: Programming Language :: Python :: 3
Classifier: Programming Language :: Python :: 3.10
Classifier: Programming Language :: Python :: 3.11
Requires-Dist: material-color-utilities-python (==0.1.5)
Requires-Dist: rich (>=12.5.1,<13.0.0)
